[
  {
    "title": "....................... rencontres, événements inattendus, personnages cachés, masqués, mises en scène destinées à duper.",
    "answer_1": "comique de mots",
    "answer_2": "comique de caractère",
    "answer_3": "comique de situation",
    "right_answer": "comique de situation"
  },
  {
    "title": "....................oppose deux mots de sens contraires à l’intérieur d’une phrase ou d’un paragraphe pour produire un effet de contraste.",
    "answer_1": "L’oxymore",
    "answer_2": "L’hyperbole",
    "answer_3": "L’antithèse ",
    "right_answer": "L’antithèse "
  },
  {
    "title": " Œil pour œil, dent pour dent. Gradation ascendante?",
    "answer_1": "Vrai",
    "answer_2": "Faux",
    "answer_3": "Je Ne Sais Pas",
    "right_answer": "Faux"
  },
  {
    "title": " C’est un conte à dormir debout. L’hyperbole?",
    "answer_1": "Vrai",
    "answer_2": "Faux",
    "answer_3": "Je Ne Sais Pas",
    "right_answer": "Vrai"
  },
  {
    "title": "Se faire tuer par sa mère en rentrant. L’oxymore?",
    "answer_1": "Vrai",
    "answer_2": "Faux",
    "answer_3": "Je Ne Sais Pas",
    "right_answer": "Faux"
  },
  {
    "title": "C’est un conte à dormir debout. L’hyperbole?",
    "answer_1": "Vrai",
    "answer_2": "Faux",
    "answer_3": "Je Ne Sais Pas",
    "right_answer": "Vrai"
  },
  {
    "title": "L’euphémisme fait suivre des termes de même nature qui, accumulés, insistent sur ce qui est exprimé de façon croissante ou décroissante et elle peut être hyperbolique.",
    "answer_1": "Vrai",
    "answer_2": "Faux",
    "answer_3": "Je Ne Sais Pas",
    "right_answer": "Faux"
  },
  {
    "title": " J’aimerais mieux une laide bien sotte Qu’une femme fort belle avec beaucoup d’esprit. L’oxymore?",
    "answer_1": "Vrai",
    "answer_2": "Faux",
    "answer_3": "Je Ne Sais Pas",
    "right_answer": "Faux"
  },
  {
    "title": " je me meurs, je suis mort, je suis enterré. Gradation descendante?",
    "answer_1": "Vrai",
    "answer_2": "Faux",
    "answer_3": "Je Ne Sais Pas",
    "right_answer": "Faux"
  },
  {
    "title": ".................... emploie des mots qui créent un effet d’exagération.",
    "answer_1": "L’oxymore",
    "answer_2": "L’hyperbole",
    "answer_3": "L’antithèse",
    "right_answer": "L’hyperbole"
  },
  {
    "title": "......................est un cas particulier de l’antithèse, il réunit à l’intérieur de la même expression deux mots dont les significations sont apparemment incompatibles.",
    "answer_1": "L’oxymore",
    "answer_2": "L’hyperbole",
    "answer_3": "L’antithèse ",
    "right_answer": "L’oxymore"
  },
  {
    "title": "(une belle horreur), (le soleil noir de la mélancolie) L’oxymore?",
    "answer_1": "Vrai",
    "answer_2": "Faux",
    "answer_3": "Je Ne Sais Pas",
    "right_answer": "Vrai"
  },
  {
    "title": "Les figures d’opposition,Elles rapprochent de manière saisissante des termes opposés de façon à marquer le lecteur.",
    "answer_1": "Vrai",
    "answer_2": "Faux",
    "answer_3": "Je Ne Sais Pas",
    "right_answer": "Vrai"
  },
  {
    "title": "Homme égalant les rois, homme approchant des Dieux. Gradation descendante?",
    "answer_1": "Vrai",
    "answer_2": "Faux",
    "answer_3": "Je Ne Sais Pas",
    "right_answer": "Faux"
  },
  {
    "title": ".................. héros entêtés ou faibles, valets plus fins que leurs maîtres, défauts d’un personnage accentués.",
    "answer_1": "comique de mots",
    "answer_2": "comique de caractère",
    "answer_3": "comique de situation",
    "right_answer": "comique de caractère"
  },
  {
    "title": "...................est une formulation indirecte qui atténue une réalité douloureuse ou choquante.",
    "answer_1": "L’antithèse",
    "answer_2": "La gradation",
    "answer_3": "L’euphémisme ",
    "right_answer": "L’euphémisme "
  },
  {
    "title": "Elle me confia son sac. Il pesait au moins une tonne! L’hyperbole? ",
    "answer_1": "Vrai",
    "answer_2": "Faux",
    "answer_3": "Je Ne Sais Pas",
    "right_answer": "Vrai"
  },
  {
    "title": "Va, je ne te hais point. L’euphémisme?",
    "answer_1": "Vrai",
    "answer_2": "Faux",
    "answer_3": "Je Ne Sais Pas",
    "right_answer": "Vrai"
  },
  {
    "title": "Va, je ne te hais point, Cette figure est une révélation indirecte (par bienséance) de l’amour de Chimène pour le meurtrier de son père.",
    "answer_1": "Vrai",
    "answer_2": "Faux",
    "answer_3": "Je Ne Sais Pas",
    "right_answer": "Vrai"
  },
  {
    "title": " L’histoire, c’est la manière de raconter cette histoire, l’ensemble de procédées choisis par le narrateur.",
    "answer_1": "Vrai",
    "answer_2": "Faux",
    "answer_3": "Je Ne Sais Pas",
    "right_answer": "Faux"
  },
  {
    "title": "........................, que l’on désigne communément par tonalité ou ton, est l’ensemble des caractéristiques d’un texte provoquant des effets particuliers sur le lecteur.",
    "answer_1": "Les registres analytiques",
    "answer_2": "Le registre littéraire",
    "answer_3": "registres de langue",
    "right_answer": "Le registre littéraire"
  },
  {
    "title": "...................... est le texte dont le but est de faire rire le lecteur.",
    "answer_1": "Le registre tragique",
    "answer_2": "Le registre littéraire",
    "answer_3": "Le registre comique ",
    "right_answer": "Le registre comique "
  },
  {
    "title": "Il existe différents types de comique: comique de gestes, comique de mots, comique de situation, comique de caractère.",
    "answer_1": "Vrai",
    "answer_2": "Faux",
    "answer_3": "Je Ne Sais Pas",
    "right_answer": "Vrai"
  },
  {
    "title": ".....................gestuelle ridicule ou répétitive, mimiques, jeux de scènes.",
    "answer_1": "comique de mots",
    "answer_2": "comique de gestes",
    "answer_3": "comique de situation",
    "right_answer": "comique de gestes"
  },
  {
    "title": "Les figures d’amplification et d’atténuation recourent à un vocabulaire qui accentue ou amoindrit ce qui est décrit et évoqué.",
    "answer_1": "Vrai",
    "answer_2": "Faux",
    "answer_3": "Je Ne Sais Pas",
    "right_answer": "Vrai"
  },
  {
    "title": "Bastonnade dans Les Fourberies de Scapin, III, 2 de Molière.",
    "answer_1": "comique de mots",
    "answer_2": "comique de gestes",
    "answer_3": "comique de situation",
    "right_answer": "comique de gestes"
  },
  {
    "title": "...................jeux avec le langage, calembours, répétitions.",
    "answer_1": "comique de mots",
    "answer_2": "comique de caractère",
    "answer_3": "comique de situation",
    "right_answer": "comique de mots"
  },
  {
    "title": "Quiproquo de L’École des femmes, II, 5 de Molière.",
    "answer_1": "comique de mots",
    "answer_2": "comique de caractère",
    "answer_3": "comique de situation",
    "right_answer": "comique de mots"
  },
  {
    "title": "Plaute et Molière ridiculisent un vieil avare.",
    "answer_1": "comique de mots",
    "answer_2": "comique de caractère",
    "answer_3": "comique de situation",
    "right_answer": "comique de caractère"
  },
  {
    "title": "Le registre tragique définit un texte qui dépeint un spectacle ou une scène tragique.",
    "answer_1": "Vrai",
    "answer_2": "Faux",
    "answer_3": "Je Ne Sais Pas",
    "right_answer": "Vrai"
  },
  {
    "title": "Dans le registre comique il s’agit souvent d’une situation et une atmosphère pesantes, d’un accomplissement d’un destin fatal comme celui d’OEdipe, de personnages impuissants et une atmosphère angoissante.",
    "answer_1": "Vrai",
    "answer_2": "Faux",
    "answer_3": "Je Ne Sais Pas",
    "right_answer": "Faux"
  },
  {
    "title": "....................... se caractérise par des termes et des formulations propres à l’univers dépeint",
    "answer_1": "Le registre littéraire",
    "answer_2": "Le registre comique",
    "answer_3": "Le registre tragique",
    "right_answer": "Le registre tragique"
  },
  {
    "title": "Le récit est un genre narratif du verbe latin recitare signifiant (dire à haute voix ), le mot récit est lié au genre de l’épopée.",
    "answer_1": "Vrai",
    "answer_2": "Faux",
    "answer_3": "Je Ne Sais Pas",
    "right_answer": "Vrai"
  },
  {
    "title": "Le récit est un « tissu narratif », il s’agit d’un processus de transformation qui fait passer un ou plusieurs personnages d’un état initial à un état final tout en s’inscrivant dans une succession temporelle et un cadre spatial comme le montre ce schéma narratif en deux étapes.",
    "answer_1": "Vrai",
    "answer_2": "Faux",
    "answer_3": "Je Ne Sais Pas",
    "right_answer": "Faux"
  },
  {
    "title": "La narration, c’est la manière de raconter cette histoire, l’ensemble de procédées choisis par le narrateur comme : illusion réelle, voix narrative.",
    "answer_1": "Vrai",
    "answer_2": "Faux",
    "answer_3": "Je Ne Sais Pas",
    "right_answer": "Vrai"
  },
  {
    "title": " ..................... le début pose un cadre spatio-temporel avec un personnages souvent caractérisé ",
    "answer_1": "Situation initiale",
    "answer_2": "Situation finale",
    "answer_3": "Situation infinie",
    "right_answer": "Situation initiale"
  },
  {
    "title": ".........................l’événement perturbateur lance une quête qui va combler un désir, une attente et va changer le cours de l’histoire.",
    "answer_1": "Comparaison",
    "answer_2": "Résolution",
    "answer_3": "Complication",
    "right_answer": "Complication"
  },
  {
    "title": "Péripéties ou intrigue constituant le cœur du récit et le héros fait ses preuves.",
    "answer_1": "Vrai",
    "answer_2": "Faux",
    "answer_3": "Je Ne Sais Pas",
    "right_answer": "Vrai"
  },
  {
    "title": ".........................,elle permet au héros d’achever sa quête, quand elle est inattendue comme dans la nouvelle, on parle de chute.",
    "answer_1": "Comparaison",
    "answer_2": "Résolution",
    "answer_3": "Complication ",
    "right_answer": "Résolution"
  },
  {
    "title": "........................retour à l’équilibre, à l’apaisement.",
    "answer_1": "Situation initiale",
    "answer_2": "Situation finale",
    "answer_3": "Situation infinie",
    "right_answer": "Situation finale"
  },
  {
    "title": "Tout récit est constitué de deux composantes fondamentales, l’histoire et la narration.",
    "answer_1": "Vrai",
    "answer_2": "Faux",
    "answer_3": "Je Ne Sais Pas",
    "right_answer": "Vrai"
  },
  {
    "title": " La narration représente l’intrigue, le temps, l’espace et les personnages.",
    "answer_1": "Vrai",
    "answer_2": "Faux",
    "answer_3": "Je Ne Sais Pas",
    "right_answer": "Faux"
  }
]
